{
    "jobs": [
        {
            "salary_min": "45",
            "locations": "Brooklyn, NY",
            "salary_type": "H",
            "date": "Thu, 15 Jun 2023 23:12:24 GMT",
            "description": " New York City and beyond.   Who you are: The Party <b>Chef</b> is responsible for leading the culinary team in executing menus... to USE's specifications at off-premise events. The Party <b>Chef</b> is also expected to collaborate with the FOH event lead in ensuring the client...",
            "salary_currency_code": "USD",
            "salary": "$45 - 60 per hour",
            "site": "",
            "url": "https://jobviewtrack.com/en-us/job-4919416e4501096c7715521711605c555714405d/23f75521cca3d2a3b277461df1041bd5.html?affid=213e213hd12344552",
            "title": "Party Chef",
            "salary_max": "60",
            "company": "Union Square Hospitality Group"
        },
        {
            "salary_min": "80000",
            "locations": "Brooklyn, NY",
            "salary_type": "Y",
            "date": "Wed, 14 Jun 2023 22:50:49 GMT",
            "description": "SUMMARY DESCRIPTION:   Williamsburg Hotel an independent lifestyle hotel is now actively seeking a dynamic <b>Chef</b>... Development:     Assist Exec. <b>Chef</b> in sourcing, pricing and creating relationships for all culinary products.  Recipe & costing...",
            "salary_currency_code": "USD",
            "salary": "$80000 - 90000 per year",
            "site": "",
            "url": "https://jobviewtrack.com/en-us/job-484f416e4501094e431100201d081d0e0b45762b01164c297e5844170600427512515a555a52/c0724c40ea4033f88225e27c194dec20.html?affid=213e213hd12344552",
            "title": "Chef De Cuisine",
            "salary_max": "90000",
            "company": "Williamsburg Hotel"
        },
        {
            "salary_min": "45000",
            "locations": "Brooklyn, NY",
            "salary_type": "Y",
            "date": "Fri, 09 Jun 2023 22:39:08 GMT",
            "description": " of their cultural identity and sense of self.   About the Role   The Head <b>Chef</b> position is an exciting opportunity for a talented... and seasoned <b>chef</b> looking to transition to meaningful, impactful work.   The Head <b>Chef</b> directs the day-to-day operations of a 3 - 7...",
            "salary_currency_code": "USD",
            "salary": "$45000 - 65000 per year",
            "site": "",
            "url": "https://jobviewtrack.com/en-us/job-181f414443443c0d4f1b4f0f6a320d0f0a4f18482a1b4f4d3f6e4501096c7417480c070d6f555712405c5c/87fe5549a387956a401f35913731f45d.html?affid=213e213hd12344552",
            "title": "Chef, In-School - Brooklyn",
            "salary_max": "65000",
            "company": "Red Rabbit"
        },
        {
            "salary_min": "45000",
            "locations": "Brooklyn, NY",
            "salary_type": "Y",
            "date": "Fri, 09 Jun 2023 22:09:58 GMT",
            "description": " of their cultural identity and sense of self.   About the Role   The Head <b>Chef</b> position is an exciting opportunity for a talented... and seasoned <b>chef</b> looking to transition to meaningful, impactful work.   The Head <b>Chef</b> directs the day-to-day operations of a 3 - 7...",
            "salary_currency_code": "USD",
            "salary": "$45000 - 65000 per year",
            "site": "",
            "url": "https://jobviewtrack.com/en-us/job-181f414443443c0d4f1b4f0f6a320d0f0a4f18482a1b4f4d3f6e4501096c7417480c070d6f555712405c5c/fa4a49ce30f6773b71c410a10177c178.html?affid=213e213hd12344552",
            "title": "Chef, In-School - Brooklyn",
            "salary_max": "65000",
            "company": "Red Rabbit"
        },
        {
            "salary_min": "78000",
            "locations": "Brooklyn, NY",
            "salary_type": "Y",
            "date": "Thu, 08 Jun 2023 02:15:42 GMT",
            "description": "Nami Nori is looking for a driven and detail-oriented Executive Sous <b>Chef</b> to lead the team for our Williamsburg... in all aspects of the job. The Executive Sous <b>Chef</b> reports to the Corporate <b>Chef</b>.   Experience in Japanese cuisine...",
            "salary_currency_code": "USD",
            "salary": "$78000 - 90000 per year",
            "site": "",
            "url": "https://jobviewtrack.com/en-us/job-4c1c416855010c1b531d560648320112160037000c15286e45484e111b075111002000040865364f011b4930424e5b2f681c0a0d520049150d413d081053762b01164c2a0f1f1f505b5b/f31cf9945878f0f6e7839bbfeaeb70a0.html?affid=213e213hd12344552",
            "title": "Executive Sous Chef",
            "salary_max": "90000",
            "company": "Nami Nori"
        },
        {
            "salary_min": "80000",
            "locations": "Brooklyn, NY",
            "salary_type": "Y",
            "date": "Wed, 07 Jun 2023 22:50:00 GMT",
            "description": ", Kentucky Derby, and NHL, MLB, NBA, NFL, and MLS All-Star Games.   Job Summary   Summary: As a Senior Sous <b>Chef</b> - Concessions... and expectations of food quality, freshness and presentation. The Sous <b>Chef</b> I also motivates, trains, develops, and directs the back...",
            "salary_currency_code": "USD",
            "salary": "$80000 - 90000 per year",
            "site": "",
            "url": "https://jobviewtrack.com/en-us/job-1a4f417e480a06015554730c1d124e240d45126a3a1c5f581d6e4501096c74114e0a07134e24004e000d1b71794e534442164f2d4f1146612b090b016412465a5d471f/6503d901362f94f0ffc7d6feea7262ad.html?affid=213e213hd12344552",
            "title": "Senior Sous Chef - Barclays Center",
            "salary_max": "90000",
            "company": "Compass Group"
        },
        {
            "salary_min": "65000",
            "locations": "Brooklyn, NY",
            "salary_type": "Y",
            "date": "Wed, 07 Jun 2023 22:41:58 GMT",
            "description": ", Kentucky Derby, and NHL, MLB, NBA, NFL, and MLS All-Star Games.   Job Summary   Summary: The Sous <b>Chef</b> position is a central..., as needed  Setting standards for <b>chef</b> table setups  Creation of prep sheets and line layout diagrams to ensure consistent and efficient...",
            "salary_currency_code": "USD",
            "salary": "$65000 per year",
            "site": "",
            "url": "https://jobviewtrack.com/en-us/job-1948416e41110d4e741b551048220602032227071c000a6855484b662c0252160020000408652648110e6b30465e5f2c1f565d5a1341/f46c17c000a93771601becf62871b97a.html?affid=213e213hd12344552",
            "title": "Sous Chef - 40/40 Club @ Barclays Center",
            "salary_max": "65000",
            "company": "Compass Group"
        },
        {
            "salary_min": "65000",
            "locations": "Brooklyn, NY",
            "salary_type": "Y",
            "date": "Wed, 07 Jun 2023 22:37:04 GMT",
            "description": ", Kentucky Derby, and NHL, MLB, NBA, NFL, and MLS All-Star Games.   Job Summary   Summary: The Sous <b>Chef</b> position is a central..., as needed  Setting standards for <b>chef</b> table setups  Creation of prep sheets and line layout diagrams to ensure consistent and efficient...",
            "salary_currency_code": "USD",
            "salary": "$65000 per year",
            "site": "",
            "url": "https://jobviewtrack.com/en-us/job-1948416e41110d4e741b551048220602032227071c000a6855484b662c0252160020000408652648110e6b30465e5f2c1f565d5a1341/1a3e35f6ed140f8e79e1f6e832534431.html?affid=213e213hd12344552",
            "title": "Sous Chef - Qatar Club @ Barclays Center",
            "salary_max": "65000",
            "company": "Compass Group"
        },
        {
            "locations": "Brooklyn, NY",
            "site": "",
            "date": "Sat, 03 Jun 2023 05:18:07 GMT",
            "url": "https://jobviewtrack.com/en-us/job-4e12414443443b1c461d4e0a06066c3317411d06001d4d0b7e4548026d2d4f1146613c130f0e0b491a0f68411819091918/e0640a6ec719379561f5c99d9688ff04.html?affid=213e213hd12344552",
            "title": "Chef in Training, Williamsburg",
            "description": "<b>Chef</b> in Training   Up to $19 - $23/hr with tips*  *Depending on experience   Base wage before tips: $16 - 18 (+ $2-4... - Noon each day and last for 9 hours and 45 minutes with a lunch break   ABOUT THE ROLE:   As a <b>Chef</b>-In-Training...",
            "company": "DIG",
            "salary": ""
        },
        {
            "locations": "Brooklyn, NY",
            "site": "",
            "date": "Fri, 26 May 2023 23:41:34 GMT",
            "url": "https://jobviewtrack.com/en-us/job-4c19417e42111c4e641c45056a220602032227071c002b190f1f19505a/b6b100b83adf9e30e616a1d52c4f6da6.html?affid=213e213hd12344552",
            "title": "Sous Chef",
            "description": " Executive Sous <b>Chef</b> with managing and organizing the activities of the Back of House and the Temaki Chefs to maintain the... and presentation required for each dish  Collaborate with Executive Sous <b>Chef</b> for menu development, holiday items, special events...",
            "company": "Nami Nori",
            "salary": ""
        },
        {
            "salary_min": "80000",
            "locations": "Brooklyn, NY",
            "salary_type": "Y",
            "date": "Fri, 26 May 2023 00:41:53 GMT",
            "description": ", Kentucky Derby, and NHL, MLB, NBA, NFL, and MLS All-Star Games.   Job Summary   Summary: As a Senior Sous <b>Chef</b> - Concessions... and expectations of food quality, freshness and presentation. The Sous <b>Chef</b> I also motivates, trains, develops, and directs the back...",
            "salary_currency_code": "USD",
            "salary": "$80000 - 90000 per year",
            "site": "",
            "url": "https://jobviewtrack.com/en-us/job-1a4f417e480a06015554730c1d124e240d45126a3a1c5f581d6e4501096c74114e0a07134e24004e000d1b71794e534442164f2d4f1146612b090b016412465a5d471f/9623644eb0bc12037bd490afa753136e.html?affid=213e213hd12344552",
            "title": "Senior Sous Chef - Barclays Center",
            "salary_max": "90000",
            "company": "Compass Group"
        },
        {
            "salary_min": "100000",
            "locations": "Brooklyn, NY",
            "salary_type": "Y",
            "date": "Thu, 25 May 2023 07:51:44 GMT",
            "description": "Description :   Union Square Hospitality Group is looking for an Executive Pastry <b>Chef</b> to join their growing team... you are: The Executive Pastry <b>Chef</b> is responsible for all pastry menu execution and development for all outlets within the hotel...",
            "salary_currency_code": "USD",
            "salary": "$100000 - 125000 per year",
            "site": "",
            "url": "https://jobviewtrack.com/en-us/job-4c19416855010c1b531d560648310f1411520d482a1b4f4d3f6855010c1b531d560648220602032224091a0758521d6e4501096c620c45001d150711000024091a0758523f6e4501096f154612575c54/e1873788506587fa97fef828cb416ff6.html?affid=213e213hd12344552",
            "title": "Executive Pastry Chef",
            "salary_max": "125000",
            "company": "Union Square Hospitality Group"
        },
        {
            "salary_min": "75000",
            "locations": "Brooklyn, NY",
            "salary_type": "Y",
            "date": "Thu, 25 May 2023 05:26:59 GMT",
            "description": " York City and beyond.   Who you are: This Pastry Sous <b>Chef</b> role is in charge of leading and overseeing our hourly pastry... production alongside the team that they oversee. This is a \u201cworking <b>chef</b>\u201d position.   What you\u2019ll do:  oversee daily pastry...",
            "salary_currency_code": "USD",
            "salary": "$75000 - 90000 per year",
            "site": "",
            "url": "https://jobviewtrack.com/en-us/job-4e4e417d4c171b1c5e54730c1d124e240d45126a3912595f4f540d27070b4176730c1d124e240d45126a3912595f4f540d37001b5476630b0d076f555712405c5c/62ce55c78a9850a68bfff4091800c1d6.html?affid=213e213hd12344552",
            "title": "Pastry Sous Chef",
            "salary_max": "90000",
            "company": "Union Square Hospitality Group"
        },
        {
            "salary_min": "90000",
            "locations": "Brooklyn, NY",
            "salary_type": "Y",
            "date": "Thu, 25 May 2023 01:11:18 GMT",
            "description": " York City and beyond.   Who you are: the \u200bExecutive Sous <b>Chef</b> for Union Square Events is responsible for the daily... production and execution of our banquet and all culinary operations. This role will support the Executive <b>Chef</b> to adapt...",
            "salary_currency_code": "USD",
            "salary": "$90000 - 105000 per year",
            "site": "",
            "url": "https://jobviewtrack.com/en-us/job-4c1c416855010c1b531d560648320112160037000c15286e45484e111b075111002000040865364f011b4930424e5b2f681c0a0d520049150d413d081053762b01164c2a0f1f1f505b5b/8aec8c07229b2c99a674e29574a8c867.html?affid=213e213hd12344552",
            "title": "Executive Sous Chef",
            "salary_max": "105000",
            "company": "Union Square Hospitality Group"
        },
        {
            "salary_min": "65000",
            "locations": "Brooklyn, NY",
            "salary_type": "Y",
            "date": "Wed, 24 May 2023 01:28:34 GMT",
            "description": ", Kentucky Derby, and NHL, MLB, NBA, NFL, and MLS All-Star Games.   Job Summary   Summary: The Sous <b>Chef</b> position is a central..., as needed  Setting standards for <b>chef</b> table setups  Creation of prep sheets and line layout diagrams to ensure consistent and efficient...",
            "salary_currency_code": "USD",
            "salary": "$65000 per year",
            "site": "",
            "url": "https://jobviewtrack.com/en-us/job-1948416e41110d4e741b551048220602032227071c000a6855484b662c0252160020000408652648110e6b30465e5f2c1f565d5a1341/d78b10659d08ec937f2f2e1629b10b67.html?affid=213e213hd12344552",
            "title": "Sous Chef - Qatar Club @ Barclays Center",
            "salary_max": "65000",
            "company": "Compass Group"
        },
        {
            "salary_min": "65000",
            "locations": "Brooklyn, NY",
            "salary_type": "Y",
            "date": "Tue, 23 May 2023 23:19:09 GMT",
            "description": ", Kentucky Derby, and NHL, MLB, NBA, NFL, and MLS All-Star Games.   Job Summary   Summary: The Sous <b>Chef</b> position is a central..., as needed  Setting standards for <b>chef</b> table setups  Creation of prep sheets and line layout diagrams to ensure consistent and efficient...",
            "salary_currency_code": "USD",
            "salary": "$65000 per year",
            "site": "",
            "url": "https://jobviewtrack.com/en-us/job-1948416e41110d4e741b551048220602032227071c000a6855484b662c0252160020000408652648110e6b30465e5f2c1f565d5a1341/83e3d5915d00e7865799296a23a8d0a9.html?affid=213e213hd12344552",
            "title": "Sous Chef - 40/40 Club @ Barclays Center",
            "salary_max": "65000",
            "company": "Compass Group"
        },
        {
            "salary_min": "90000",
            "locations": "Brooklyn, NY",
            "salary_type": "Y",
            "date": "Sun, 21 May 2023 07:27:09 GMT",
            "description": " of a career where you can flourish.   Job Summary   Working as an Executive <b>Chef</b>, you are responsible for overseeing all culinary...",
            "salary_currency_code": "USD",
            "salary": "$90000 - 95000 per year",
            "site": "",
            "url": "https://jobviewtrack.com/en-us/job-1e1a416855010c1b531d560648220602032237000c15286e45484e111b07511121515a535a5350/e9f908645c50e65dc7549a16037699e3.html?affid=213e213hd12344552",
            "title": "EXECUTIVE CHEF",
            "salary_max": "95000",
            "company": "Compass Group"
        },
        {
            "salary_min": "90000",
            "locations": "Brooklyn, NY",
            "salary_type": "Y",
            "date": "Sat, 20 May 2023 22:37:51 GMT",
            "description": " of a career where you can flourish.   Job Summary   Working as an Executive <b>Chef</b>, you are responsible for overseeing all culinary...",
            "salary_currency_code": "USD",
            "salary": "$90000 - 95000 per year",
            "site": "",
            "url": "https://jobviewtrack.com/en-us/job-1e1a416855010c1b531d560648220602032237000c15286e45484e111b07511121515a535a5350/7c74d853ee0ba3ac913faa70859b5f76.html?affid=213e213hd12344552",
            "title": "EXECUTIVE CHEF",
            "salary_max": "95000",
            "company": "Compass Group"
        },
        {
            "salary_min": "70000",
            "locations": "Brooklyn, NY",
            "salary_type": "Y",
            "date": "Fri, 28 Apr 2023 04:00:27 GMT",
            "description": "The role\u2026   At Soho House a Sous <b>Chef</b> is motivated to positively influence the kitchen team to follow the direction... of Executive <b>Chef</b> and Executive Sous <b>Chef</b> in planning, organizing and managing the Kitchen Department according to company policies...",
            "salary_currency_code": "USD",
            "salary": "$70000 - 85000 per year",
            "site": "",
            "url": "https://jobviewtrack.com/en-us/job-4c19417e42111c4e641c45056a220602032227071c002b190f1f19505a/43fcaf3546c142efd7ce345f5402044b.html?affid=213e213hd12344552",
            "title": "Sous Chef",
            "salary_max": "85000",
            "company": "Soho House"
        },
        {
            "locations": "Brooklyn, NY",
            "site": "",
            "date": "Fri, 21 Apr 2023 23:19:44 GMT",
            "url": "https://jobviewtrack.com/en-us/job-1c18417e58170707073748060e632d0f0046763b1c0042423c1f1f565b5a12/170d66e1a50efd697ebd7c823c0ebc42.html?affid=213e213hd12344552",
            "title": "SUSHI CHEF",
            "description": ".   Our Sushi <b>Chef</b> someone who is familiar with a wide variety of sushi recipes and is capable of delivering quality product...",
            "company": "Arirang Hibachi Steakhouse",
            "salary": ""
        }
    ],
    "hits": 49,
    "response_time": 0.0992331504821777,
    "type": "JOBS",
    "pages": 3
}